Metadata-Version: 2.1
Name: nonebot-plugin-muteme
Version: 0.0.5
Summary: 适用于nonebot2 v11的禁言自己插件 高仿 @能干辉 的muteme
Home-page: https://github.com/XTxiaoting14332/nonebot-plugin-muteme
Author: NightWind
Author-email: 2125714976@qq.com
License: UNKNOWN
Platform: UNKNOWN
License-File: LICENSE
Requires-Dist: nonebot-adapter-onebot
Requires-Dist: nonebot2
